apptrackr/main.py
apptrackr/model/__init__.py
apptrackr/model/model.py
apptrackr/model/utils.py
apptrackr/modules/config.py
apptrackr/modules/storage.py
apptrackr-0.2.4.dist-info/METADATA
apptrackr-0.2.4.dist-info/WHEEL
apptrackr-0.2.4.dist-info/entry_points.txt
apptrackr-0.2.4.dist-info/RECORD
