Metadata-Version: 2.1
Name: apptrackr
Version: 0.2.4
Summary: 
License: MIT
Author: Aradhya Tripathi
Author-email: 67282231+Aradhya-Tripathi@users.noreply.github.com
Requires-Python: >=3.12,<4.0
Classifier: License :: OSI Approved :: MIT License
Classifier: Programming Language :: Python :: 3
Classifier: Programming Language :: Python :: 3.12
Requires-Dist: humanize (>=4.9.0,<5.0.0)
Requires-Dist: peewee (>=3.17.1,<4.0.0)
Requires-Dist: questionary (>=2.0.1,<3.0.0)
Requires-Dist: requests (>=2.31.0,<3.0.0)
Requires-Dist: trogon (>=0.5.0,<0.6.0)
Requires-Dist: typer (>=0.12.0,<0.13.0)
